README
setup.py
phrank/__init__.py
phrank/utils.py
phrank.egg-info/PKG-INFO
phrank.egg-info/SOURCES.txt
phrank.egg-info/dependency_links.txt
phrank.egg-info/not-zip-safe
phrank.egg-info/top_level.txt