Metadata-Version: 1.0
Name: phrank
Version: 1.6
Summary: Measuring phenotype set similarity
Home-page: https://bitbucket.org/bejerano/phrank/
Author: Bejerano Lab
Author-email: kjag@cs.stanford.edu
License: MIT
Platform: UNKNOWN
